ingraph/aws/__init__.pyi
ingraph/aws/alexa_ask.pyi
ingraph/aws/aws_accessanalyzer.pyi
ingraph/aws/aws_acmpca.pyi
ingraph/aws/aws_amazonmq.pyi
ingraph/aws/aws_amplify.pyi
ingraph/aws/aws_apigateway.pyi
ingraph/aws/aws_apigatewayv2.pyi
ingraph/aws/aws_appconfig.pyi
ingraph/aws/aws_appflow.pyi
ingraph/aws/aws_applicationautoscaling.pyi
ingraph/aws/aws_applicationinsights.pyi
ingraph/aws/aws_appmesh.pyi
ingraph/aws/aws_appstream.pyi
ingraph/aws/aws_appsync.pyi
ingraph/aws/aws_athena.pyi
ingraph/aws/aws_auditmanager.pyi
ingraph/aws/aws_autoscaling.pyi
ingraph/aws/aws_autoscalingplans.pyi
ingraph/aws/aws_backup.pyi
ingraph/aws/aws_batch.pyi
ingraph/aws/aws_budgets.pyi
ingraph/aws/aws_cassandra.pyi
ingraph/aws/aws_ce.pyi
ingraph/aws/aws_certificatemanager.pyi
ingraph/aws/aws_chatbot.pyi
ingraph/aws/aws_cloud9.pyi
ingraph/aws/aws_cloudformation.pyi
ingraph/aws/aws_cloudfront.pyi
ingraph/aws/aws_cloudtrail.pyi
ingraph/aws/aws_cloudwatch.pyi
ingraph/aws/aws_codeartifact.pyi
ingraph/aws/aws_codebuild.pyi
ingraph/aws/aws_codecommit.pyi
ingraph/aws/aws_codedeploy.pyi
ingraph/aws/aws_codeguruprofiler.pyi
ingraph/aws/aws_codegurureviewer.pyi
ingraph/aws/aws_codepipeline.pyi
ingraph/aws/aws_codestar.pyi
ingraph/aws/aws_codestarconnections.pyi
ingraph/aws/aws_codestarnotifications.pyi
ingraph/aws/aws_cognito.pyi
ingraph/aws/aws_config.pyi
ingraph/aws/aws_databrew.pyi
ingraph/aws/aws_datapipeline.pyi
ingraph/aws/aws_datasync.pyi
ingraph/aws/aws_dax.pyi
ingraph/aws/aws_detective.pyi
ingraph/aws/aws_devopsguru.pyi
ingraph/aws/aws_directoryservice.pyi
ingraph/aws/aws_dlm.pyi
ingraph/aws/aws_dms.pyi
ingraph/aws/aws_docdb.pyi
ingraph/aws/aws_dynamodb.pyi
ingraph/aws/aws_ec2.pyi
ingraph/aws/aws_ecr.pyi
ingraph/aws/aws_ecs.pyi
ingraph/aws/aws_efs.pyi
ingraph/aws/aws_eks.pyi
ingraph/aws/aws_elasticache.pyi
ingraph/aws/aws_elasticbeanstalk.pyi
ingraph/aws/aws_elasticloadbalancing.pyi
ingraph/aws/aws_elasticloadbalancingv2.pyi
ingraph/aws/aws_elasticsearch.pyi
ingraph/aws/aws_emr.pyi
ingraph.aws-0.0.37.dist-info/LICENSE
ingraph.aws-0.0.37.dist-info/METADATA
ingraph.aws-0.0.37.dist-info/WHEEL
ingraph.aws-0.0.37.dist-info/top_level.txt
ingraph.aws-0.0.37.dist-info/RECORD
