Metadata-Version: 2.1
Name: ingraph.aws
Version: 0.0.37
Summary: AWS CloudFormation resources for InGraph.
Home-page: https://lifa.dev/ingraph
Author: lifa.dev
Author-email: croak@lifa.dev
License: Apache-2.0
Project-URL: Repository, https://github.com/lifadev/ingraph-aws
Platform: any
Classifier: Programming Language :: Python
Classifier: Programming Language :: Python :: 3.8
Classifier: License :: OSI Approved
Classifier: License :: OSI Approved :: Apache Software License
Requires-Python: <4.0,>=3.8
Provides-Extra: dev
Requires-Dist: autoflake ; extra == 'dev'
Requires-Dist: black ; extra == 'dev'
Requires-Dist: isort ; extra == 'dev'
Requires-Dist: jinja2 ; extra == 'dev'
Requires-Dist: mypy ; extra == 'dev'
Requires-Dist: pytest ; extra == 'dev'
Requires-Dist: pytest-cov ; extra == 'dev'
Requires-Dist: pytest-mock ; extra == 'dev'
Requires-Dist: pytest-xdist ; extra == 'dev'
Requires-Dist: rope ; extra == 'dev'
Requires-Dist: toml ; extra == 'dev'
Requires-Dist: twine ; extra == 'dev'
